text_cleaning/__init__.py
text_cleaning/text_cleaning.py
text_cleaning-0.0.5.dist-info/LICENSE
text_cleaning-0.0.5.dist-info/METADATA
text_cleaning-0.0.5.dist-info/WHEEL
text_cleaning-0.0.5.dist-info/top_level.txt
text_cleaning-0.0.5.dist-info/RECORD
