Metadata-Version: 2.1
Name: text-cleaning
Version: 0.0.5
Summary: Text Cleaning
Author: Piyush Mittal
Author-email: <piyushmittal2192@gmail.com>
License: UNKNOWN
Platform: UNKNOWN
License-File: LICENSE
Requires-Dist: more-itertools
Requires-Dist: sklearn
Requires-Dist: numpy
Requires-Dist: levenshtein
